{
  "Moonworks:Accelerator": {
    "NAME": "액셀러레이터",
    "DESCRIPTION": "*액셀러레이터 를 !M! 얻습니다.",
    "EXTENDED_DESCRIPTION": ["액셀러레이터", "전투 중에 카드를 생성할 때 마다 그 카드를 1 장 추가로 생성합니다. NL #y상태이상, #y저주, 혹은 #y매지컬 카드에는 적용되지 않습니다. ","가능하다면, 추가로 [E] 를 사용하여 복사한 모든 카드를 강화합니다."]
  },
  "Moonworks:AccelHyper": {
    "NAME": "액셀 하이퍼",
    "DESCRIPTION": "이번 턴에 사용하는 다음 공격과 스킬카드가 두 번 사용됩니다. NL 소멸.",
    "UPGRADE_DESCRIPTION": "이번 턴에 사용하는 다음 공격과 스킬카드가 두 번 사용됩니다."
  },
  "Moonworks:AirStrike": {
    "NAME": "공중 폭격",
    "DESCRIPTION": "모든 적에게 !D! moonworks:확산 *피해 를 줍니다. NL Purge."
  },
  "Moonworks:Ambush": {
    "NAME": "기습",
    "DESCRIPTION": "취약 을 !M! 부여합니다.. NL 그 뒤 피해를 !D! 줍니다.",
    "EXTENDED_DESCRIPTION": ["이 공격이 moonworks:관통 합니다."]
  },
  "Moonworks:AngelHand": {
    "NAME": "앤젤 핸드",
    "DESCRIPTION": "보존. NL 방어도 를 !B! 얻습니다. NL 보존 시, 이 카드는 *데빌 *핸드 가 됩니다."
  },
  "Moonworks:AnotherUltimateWeapon": {
    "NAME": "또 하나의 최종병기",
    "DESCRIPTION": "힘 을 X 만큼, 방어도 를 그 5배 만큼 얻습니다.",
    "UPGRADE_DESCRIPTION": "힘 을 X+1 만큼, 방어도 를 그 5배 만큼 얻습니다.",
    "EXTENDED_DESCRIPTION": ["힘 을 X 만큼, 방어도 를 그 5배 만큼 추가로 얻습니다."]
  },
  "Moonworks:Assault": {
    "NAME": "돌격",
    "DESCRIPTION": "moonworks:관통 *피해 를 !D! 줍니다.",
    "EXTENDED_DESCRIPTION": ["*관통 의 효과가 두 배가 됩니다."]
  },
  "Moonworks:AwakeningOfTalent": {
    "NAME": "재능 각성",
    "DESCRIPTION": "피해를 !D! 줍니다. NL 방어도 를 !B! 얻습니다. NL 카드를 !M! 장 뽑습니다. NL 이 카드로 적을 처치할 경우, [E] 를 얻습니다.",
    "EXTENDED_DESCRIPTION": ["[E] 를 얻습니다."]
  },
  "Moonworks:BackdoorTrade": {
    "NAME": "뒷거래",
    "DESCRIPTION": "*노르마 레벨을 !Moonworks:SecondMagic! 만큼 올립니다. NL 소멸.",
    "EXTENDED_DESCRIPTION": ["소멸 하지 않고, 카드를 !M! 장 뽑습니다","카드를 !M! 장 뽑습니다."]
  },
  "Moonworks:BeastWitch": {
    "NAME": "야수 마녀",
    "DESCRIPTION": "피해를 !D! 줍니다. NL 임시 힘 을 !M! 얻습니다.",
    "EXTENDED_DESCRIPTION": ["피해가 2 증가합니다."]
  },
  "Moonworks:BeyondHell": {
    "NAME": "수라장 모드",
    "DESCRIPTION": "잃은 체력 !Moonworks:InvertedNumber! 마다 활력 을 !M! 얻습니다. NL 소멸.",
    "EXTENDED_DESCRIPTION": ["이제 잃은 체력 3 마다 활력을 얻습니다."]
  },
  "Moonworks:BigBangBell": {
    "NAME": "빅뱅 벨",
    "DESCRIPTION": "적에게 공격할 의도가 없을 때, 피해를 !M! 줍니다. NL 이 피해는 매 턴 마다 증가합니다.",
    "EXTENDED_DESCRIPTION": ["기본 피해가 5 증가합니다."]
  },
  "Moonworks:BigMagnum": {
    "NAME": "빅 매그넘",
    "DESCRIPTION": "체력을 !Moonworks:InvertedNumber! 잃습니다. NL 활력 을 !M! 얻습니다. NL 힘 을 !Moonworks:SecondMagic! 얻습니다. NL 소멸.",
    "EXTENDED_DESCRIPTION": ["힘 을 추가로 X 얻습니다.","비빅 매그넘","비비빅 매그넘"]
  },
  "Moonworks:BigRocketCannon": {
    "NAME": "빅 로켓포",
    "DESCRIPTION": "moonworks:확산 *피해 를 !D! 줍니다. NL *공중 *폭격 한 장을 [#FFF6E2]뽑을 카드 더미에 섞어 넣습니다. NL Purge."
  },
  "Moonworks:BindingChains": {
    "NAME": "속박의 사슬",
    "DESCRIPTION": "적의 힘 을 이번 턴 동안 !M! 낮춥니다. moonworks:확산. NL 이번 전투 동안 효과가 4 감소합니다.",
    "EXTENDED_DESCRIPTION": ["부식된 사슬","사슬이 거의 완전히 바스라져 버렸습니다.","I can't play this card."]
  },
  "Moonworks:Blazing": {
    "NAME": "블레이징!",
    "DESCRIPTION": "턴 시작시, 힘 을 !M! 얻고 민첩 이 !Moonworks:SecondMagic! 됩니다."
  },
  "Moonworks:BlueCrowTheSecond": {
    "NAME": "블루 크로우",
    "DESCRIPTION": "피해를 !D! 줍니다. NL 방어도 를 !B! 얻습니다. NL 손에 있는 *공격 카드 한 장당 얻는 방어도가 2 증가합니다.",
    "UPGRADE_DESCRIPTION": "보존. NL 피해를 !D! 줍니다. NL 방어도 를 !B! 얻습니다. NL 손에 있는 *공격 카드 한 장당 얻는 방어도가 2 증가합니다.",
    "EXTENDED_DESCRIPTION": ["블루 크로우 더 세컨드"]
  },
  "Moonworks:Bloodlust": {
    "NAME": "피의 욕망",
    "DESCRIPTION": "moonworks:사용횟수 !Moonworks:SecondMagic!. NL 턴 시작 시 피해를 4 받습니다. 공격 카드를 사용할 때 마다 체력을 !M! 회복합니다. NL 사용시 이 카드를 버립니다.",
    "EXTENDED_DESCRIPTION": ["당신의 욕망이 가라앉았습니다."]
  },
  "Moonworks:CastOff": {
    "NAME": "캐스트 오프",
    "DESCRIPTION": "방어도 를 전부 잃습니다. NL 잃은 방어도 만큼 활력 을 얻습니다. NL 소멸.",
    "EXTENDED_DESCRIPTION": ["굳건함 을 5 얻습니다."]
  },
  "Moonworks:CloudOfSeagulls": {
    "NAME": "갈매기 떼",
    "DESCRIPTION": "무작위 대상에게 !D! 의 moonworks:고정 피해를 !Moonworks:SecondMagic! 번 줍니다. NL 뽑을 카드 더미에 *조나단 *러쉬 를 !M! 장 섞어 넣습니다.",
    "UPGRADE_DESCRIPTION": "무작위 적에게 !D! 의 moonworks:고정 피해를 !Moonworks:SecondMagic! 번 줍니다. NL 뽑을 카드 더미에 *조나단 *러쉬 를 !M! 장 섞어 넣습니다",
    "EXTENDED_DESCRIPTION": ["카드를 한 장 뽑습니다.","무작위 대상에게 !D! 피해를 줍니다. NL 뽑을 카드 더미에 *조나단 *러쉬 를 !M! 장 섞어 넣습니다"]
  },
  "Moonworks:CompletionReward": {
    "NAME": "성공 보수",
    "DESCRIPTION": "이번 전투 동안 사용한 카드의 수 만큼 피해를 줍니다. moonworks:초기화. NL (피해를 !D! 줍니다.)",
    "UPGRADE_DESCRIPTION": "이번 전투 동안 사용한 카드의 수 만큼 피해를 줍니다. 절반 moonworks:초기화. NL (피해를 !D! 줍니다.)",
    "EXTENDED_DESCRIPTION": ["피해가 3 증가합니다."]
  },
  "Moonworks:CookingTime": {
    "NAME": "쿠킹 타임",
    "DESCRIPTION": "모든 대상이 체력을 !M! 회복합니다. 회복시킨 체력 만큼 피해를 줍니다. NL 소멸.",
    "EXTENDED_DESCRIPTION": ["회복량이 3 증가합니다."]
  },
  "Moonworks:CrystalBarrier": {
    "NAME": "수정 방벽",
    "DESCRIPTION": "턴 시작시에 방어도 가 사라지지 않습니다. NL *판금 *갑옷 을 !M! 얻습니다."
  },
  "Moonworks:DarkSideOfBusiness": {
    "NAME": "어둠의 자금조달",
    "DESCRIPTION": "*노르마 를 전부 잃습니다. NL 잃은 *노르마 만큼의 스톡을 가진  moonworks:매지컬 카드 3장 중 1장을 선택합니다. NL 소멸.",
    "UPGRADE_DESCRIPTION": "*노르마 를 전부 잃습니다. NL 잃은 *노르마 만큼의 사용 횟수를 가진 강화된 moonworks:매지컬 카드 3장 중 1장을 선택합니다. NL 소멸."
  },
  "Moonworks:Dash": {
    "NAME": "대시!",
    "DESCRIPTION": "[E] 를 얻습니다. NL 소멸.",
    "UPGRADE_DESCRIPTION": "[E] [E] 를 얻습니다. NL 소멸.",
    "EXTENDED_DESCRIPTION": ["방어도 를 5 얻습니다."]
  },
  "Moonworks:Defend": {
    "NAME": "수비",
    "DESCRIPTION": "방어도 를 !B! 얻습니다.",
    "EXTENDED_DESCRIPTION": ["방어도 가 1 증가합니다.", "방어도 가 1 증가합니다."]
  },
  "Moonworks:DeltaField": {
    "NAME": "델타 필드",
    "DESCRIPTION": "모든 적에게 취약 을 !M! 부여하고 임시 힘 을 !Moonworks:SecondMagic! 감소시킵니다."
  },
  "Moonworks:DeployBits": {
    "NAME": "비트 전개",
    "DESCRIPTION": "총 !Moonworks:SecondMagic! 의 방어도 와 활력 을 무작위로 분배하여 얻습니다.",
    "EXTENDED_DESCRIPTION": ["비트가 3개 감소하지만 비트 분배가 moonworks:최적화 됩니다."]
  },
  "Moonworks:DesperateModification": {
    "NAME": "막장 개조",
    "DESCRIPTION": "피해를 !D! 줍니다. NL 적이 공격할 의도가 있다면 대신 방어도 를 !M! 얻고 소멸 합니다.",
    "EXTENDED_DESCRIPTION": ["방어도 를 !B! 얻습니다. NL 소멸."]
  },
  "Moonworks:DevilHand": {
    "NAME": "데빌 핸드",
    "DESCRIPTION": "보존. NL 피해를 !D! 줍니다. NL 보존 시, 이 카드는 *앤젤 *핸드 가 됩니다."
  },
  "Moonworks:Dinner": {
    "NAME": "디너",
    "DESCRIPTION": "모든 대상에게 재생 을 !M! 부여합니다. NL 소멸.",
    "EXTENDED_DESCRIPTION": ["부여한 재생 만큼 방어도 를 얻습니다."]
  },
  "Moonworks:Encore": {
    "NAME": "Encore",
    "DESCRIPTION": "The last card you play each turn has it's *effect used at the start of your turn.",
    "EXTENDED_DESCRIPTION": ["Gain Block equal to the amount of Regen applied."]
  },
  "Moonworks:EvilMastermind": {
    "NAME": "악의 두목",
    "DESCRIPTION": "다른 *악의 *두목 을 제외한 모든 *트랩 카드의 *효과 를 무작위 적을 대상으로 발동시킵니다.",
    "UPGRADE_DESCRIPTION": "선천성. NL 다른 *악의 *두목 을 제외한 모든 *트랩 카드의 *효과 를 무작위 적을 대상으로 발동시킵니다.",
    "EXTENDED_DESCRIPTION":
    ["선천성. NL ",
      " NL 소멸.",
      "다음 *트랩 의 *효과 를 무작위 적을 대상으로 발동시킵니다: ",
      " NL Plus *",
      " 더.",
      " 번.",
      " 번."]
  },
  "Moonworks:EvilSpyWorkExecution": {
    "NAME": "악의 공작 활동 실행",
    "DESCRIPTION": "Autoplay. NL 모든 적에게 피해를 !D! 줍니다. NL 카드를 !M! 장 뽑습니다. NL Purge.",
    "UPGRADE_DESCRIPTION": "Autoplay. NL 모든 적에게 피해를 !D! 줍니다. NL 카드를 !M! 장 뽑습니다. NL Purge."
  },
  "Moonworks:EvilSpyWorkPreparation": {
    "NAME": "악의 공작 활동 준비",
    "DESCRIPTION": "뽑을 카드 더미에 *악의 *공작 *활동 *실행 을 !M! 장 섞어 넣습니다."
  },
  "Moonworks:ExtendedPhotonRifle": {
    "NAME": "연장 포톤 라이플",
    "DESCRIPTION": "피해를 !D! 만큼 X 회 줍니다. 이 카드는 힘 을 !Moonworks:SecondMagic! 배로 적용받습니다."
  },
  "Moonworks:ExtraordinarySpecs": {
    "NAME": "Extraordinary Specs",
    "DESCRIPTION": "Gain !M! temporary Strength and Dexterity. NL Draw !Moonworks:SecondMagic! card. NL Exhaust."
  },
  "Moonworks:FinalBattle": {
    "NAME": "파이널 배틀",
    "DESCRIPTION": "다음 !M! 턴 동안, 모두의 공격이 두배의 피해를 줍니다."
  },
  "Moonworks:FinalSurgery": {
    "NAME": "마무리 수술",
    "DESCRIPTION": "피해를 !D! 줍니다. NL 적이 취약 혹은 moonworks:오버히트 상태라면, 한번 더 피해를 !D! 줍니다."
  },
  "Moonworks:Flamethrower": {
    "NAME": "화염방사기",
    "DESCRIPTION": "moonworks:사용횟수 !Moonworks:SecondMagic!. NL 카드를 사용할 때 마다 적에게 !M! moonworks:고정 피해를 줍니다. NL 사용 시 이 카드를 버립니다.",
    "EXTENDED_DESCRIPTION": ["화염방사기의 연료가 다 떨어졌습니다."]
  },
  "Moonworks:ForcedRevival": {
    "NAME": "강제 소생",
    "DESCRIPTION": "체력을 !M! 회복합니다. NL [E] 를 얻습니다. NL 취약 을 !Moonworks:InvertedNumber! 받습니다. NL 소멸.",
    "UPGRADE_DESCRIPTION": "체력을 !M! 회복합니다. NL [E] [E] 를 얻습니다. NL 취약 을 !Moonworks:InvertedNumber! 받습니다. NL 소멸.",
    "EXTENDED_DESCRIPTION": ["약화를 !Moonworks:InvertedNumber! 얻지만, 에너지 를 2 배로 만듭니다."]
  },
  "Moonworks:FullSpeedAlicianrone": {
    "NAME": "달려나가는 앨리시안로네",
    "DESCRIPTION": "피해를 !D! 줍니다. NL 다음 턴에, 카드를 !M! 장 추가로 뽑습니다.",
    "EXTENDED_DESCRIPTION": ["이제 모든 적에게 피해를 줍니다."]
  },
  "Moonworks:Gamble": {
    "NAME": "갬블!",
    "DESCRIPTION": "무작위 대상이 죽습니다.",
    "UPGRADE_DESCRIPTION": "보존. NL 무작위 대상이 죽습니다."
  },
  "Moonworks:GoAway": {
    "NAME": "저리가",
    "DESCRIPTION": "휘발성. NL 이번 턴 동안 대상을 moonworks:기절 시킵니다. NL 소멸.",
    "UPGRADE_DESCRIPTION": "이번 턴 동안 대상을 moonworks:기절 시킵니다. NL 소멸.",
    "EXTENDED_DESCRIPTION": ["대상을 전투에서 제외합니다. NL 대상이 무작위 층에서 다시 나타납니다."]
  },
  "Moonworks:GoldenEgg": {
    "NAME": "황금알",
    "DESCRIPTION": "방어도 를 !B! 얻습니다. NL 무작위 *공격 카드를 뽑을 카드 더미에 섞어 넣습니다.",
    "EXTENDED_DESCRIPTION": ["카드를 섞는 대신 손에 가져옵니다."]
  },
  "Moonworks:Heat300Percent": {
    "NAME": "히트 300%",
    "DESCRIPTION": "moonworks:오버히트 를 !M! 부여합니다. NL 소멸.",
    "EXTENDED_DESCRIPTION": ["부여한 *오버히트 의 50%를 무작위 대상에게 추가로 부여합니다."]
  },
  "Moonworks:HolyNight": {
    "NAME": "거룩한 밤",
    "DESCRIPTION": "턴 시작시, 카드를 !M! 장 추가로 뽑습니다.",
    "UPGRADE_DESCRIPTION": "선천성. NL 턴 시작시, 카드를 !M! 장 추가로 뽑습니다.",
    "EXTENDED_DESCRIPTION": ["가능하다면, 추가로 [E] 를 사용하며 효과를 두배로 강화합니다."]
  },
  "Moonworks:ImmovableObject": {
    "NAME": "움직일 수 없는 물체",
    "DESCRIPTION": "방어도 를 !B! 얻습니다. NL 다음 !M! 턴 동안 방어도 가 사라지지 않지만 공격 카드를 사용할 수 없습니다. NL 소멸."
  },
  "Moonworks:ImOnFire": {
    "NAME": "불타오른다!",
    "DESCRIPTION": "활력 을 !M! 얻고 취약 을 !Moonworks:SecondMagic! 받습니다.",
    "EXTENDED_DESCRIPTION": ["얻는 활력이 10 감소하고, 이번 턴 동안 공격이 두 배의 피해를 줍니다."]
  },
  "Moonworks:IndiscriminateFireSupport": {
    "NAME": "무차별 화력지원",
    "DESCRIPTION": "모든 적에게 !D! 피해를 X 번 줍니다. NL 뽑을 카드 더미에 어지러움 을 !Moonworks:InvertedNumber! 장 섞어 넣습니다.",
    "EXTENDED_DESCRIPTION": ["섞어넣는 어지러움 이 1 장 감소합니다."]
  },
  "Moonworks:IntelligenceOfficer": {
    "NAME": "첩보원",
    "DESCRIPTION": "예지 !M!. 예지한... NL 공격 카드마다: 활력 을 !Moonworks:SecondMagic! 얻습니다. NL 스킬 카드마다: moonworks:굳건함 을 !Moonworks:SecondMagic! 얻습니다. NL 그 외의 카드마다: 카드를 1 장 뽑습니다."
  },
  "Moonworks:JonathanRush": {
    "NAME": "조나단 러쉬",
    "DESCRIPTION": "Autoplay. NL 무작위 적에게 피해를 !D! 줍니다. NL 이번 전투 동안 모든 *조나단 *러쉬 의 피해가 !M! 증가합니다.",
    "UPGRADE_DESCRIPTION": "Autoplay. NL 무작위 적에게 피해를 !D! 줍니다. NL 이번 전투 동안 모든 *조나단 *러쉬 의 피해가 !M! 증가합니다."
  },
  "Moonworks:LeapThroughSpacetime": {
    "NAME": "Leap Through Spacetime",
    "DESCRIPTION": "Choose 1: NL Leap Through Space. NL Leap Through Time."
  },
  "Moonworks:LeapThroughSpace": {
    "NAME": "Leap Through Space",
    "DESCRIPTION": "You can see what cards you will draw next turn. You may freely add any to your hand, at the cost of 1 less draw next turn."
  },
  "Moonworks:LeapThroughTime": {
    "NAME": "Leap Through Time",
    "DESCRIPTION": "You can see the next intents for ALL enemies."
  },
  "Moonworks:LongDistanceShot": {
    "NAME": "원거리 사격",
    "DESCRIPTION": "피해를 !D! 줍니다. moonworks:관통. NL *노르마 레벨이 오를 때 마다 이 카드를 뽑습니다.",
    "EXTENDED_DESCRIPTION": ["휘발성. NL 피해를 !D! 줍니다. NL 소멸.",
      "사용횟수가 남아 있을 경우 카드를 !M! 장 뽑습니다. 사용횟수: !Moonworks:SecondMagic!."]
  },
  "Moonworks:LuckyCharm": {
    "NAME": "행운의 부적",
    "DESCRIPTION": "moonworks:사용횟수 !Moonworks:SecondMagic!. NL 턴 시작시, [E] 를 얻습니다. NL 사용 시 최대 3 [E] 를 소모하여 moonworks:사용횟수 를 보충합니다.",
    "EXTENDED_DESCRIPTION": ["부적의 행운이 다 해 버렸습니다."]
  },
  "Moonworks:LulusLuckyEgg": {
    "NAME": "룰루의 럭키 에그",
    "DESCRIPTION": "방어도를 !B! 얻습니다. NL 다음 세 효과중 하나가 무작위로 발동합니다 NL 카드를 !M! 장 뽑습니다. NL 이제 방어도를 !M! 회 얻습니다. NL 임시 민첩 을 !M! 얻습니다."
  },
  "Moonworks:MagicalInferno": {
    "NAME": "매지컬 인페르노",
    "DESCRIPTION": "모든 적에게 !D! moonworks:확산 *피해 를 줍니다. NL 활력 을 !M! 얻습니다. NL Exhaustive !stslib:ex!.",
    "EXTENDED_DESCRIPTION": ["진 매지컬 인페르노"]
  },
  "Moonworks:MagicalMassacre": {
    "NAME": "살육 마법",
    "DESCRIPTION": "체력이 가장 높은 적이 체력과 최대 체력을 !M! 잃습니다. NL moonworks:굳건함 을 !Moonworks:SecondMagic! 얻습니다. NL Exhaustive !stslib:ex!.",
    "EXTENDED_DESCRIPTION": ["진 살육마법"]
  },
  "Moonworks:MagicalRevenge": {
    "NAME": "매지컬 리벤지",
    "DESCRIPTION": "잃은 체력의 !D! % 만큼의 moonworks:복수 피해를 주고 !M! % 만큼 moonworks:생명흡수 합니다. NL (피해를 !Moonworks:SecondMagic! 줍니다.) NL Exhaustive !stslib:ex!.",
    "EXTENDED_DESCRIPTION": ["진 매지컬 리벤지"]
  },
  "Moonworks:MeltingMemories": {
    "NAME": "녹아가는 기억",
    "DESCRIPTION": "*노르마 를 전부 잃습니다. NL 매 턴 처음 사용하는 카드가 moonworks:기억 으로 *전환 됩니다. NL 매 턴 마다 *노르마 를 0 씩 복구합니다",
    "UPGRADE_DESCRIPTION": "*노르마 를 전부 잃습니다. NL 매 턴 처음 사용하는 카드가 moonworks:기억 으로 *전환 된 뒤 강화됩니다. NL 매 턴 마다 *노르마 를 0 씩 복구합니다",
    "EXTENDED_DESCRIPTION": ["기억 전환","비용이 1 이상인 #y공격 또는 #y스킬 카드만 전환할 수 있습니다. 전환 가능한 카드가 아닐 경우 전환은 실패합니다."]
  },
  "Moonworks:Mimic": {
    "NAME": "흉내내기",
    "DESCRIPTION": "손에 있는 카드를 한 장 선택합니다. 다음 턴에, 카드를 뽑지 않고 대신 선택된 카드를 !M! 장 복사해 손에 가져옵니다.",
    "EXTENDED_DESCRIPTION": ["카드를 1장 추가로 가져옵니다."]
  },
  "Moonworks:MetallicMonocoque": {
    "NAME": "통짜 금속",
    "DESCRIPTION": "받는 *직접피해 를 !M! 줄입니다. NL 받는 *간접피해 를 !Moonworks:SecondMagic! 줄입니다.",
    "EXTENDED_DESCRIPTION": ["직접피해와 간접피해", "일반적으로, NL 상대의 공격으로 받은 피해는 #y직접피해 로 간주됩니다. NL 가시 혹은 카드로 받은 피해는 #y간접피해 로 간주됩니다."]
  },
  "Moonworks:MiracleRedBeanIceCream": {
    "NAME": "미라클 팦바",
    "DESCRIPTION": "moonworks:사용횟수 !Moonworks:SecondMagic!. NL 임시 힘 을 !M! 얻습니다. NL 사용시 소멸 합니다. NL 소멸 시 체력을 5 회복합니다.",
    "EXTENDED_DESCRIPTION": ["팥바를 다 먹어버렸습니다."]
  },
  "Moonworks:MiracleWalker": {
    "NAME": "미라클 워커",
    "DESCRIPTION": "이 카드가 변환 될 때 마다, 이번 턴 동안 비용이 0 이 됩니다.",
    "UPGRADE_DESCRIPTION": "이 카드가 변환 될 때 마다, 이번 턴 동안 비용이 0 이 됩니다. NL 변환 된 카드가 강화됩니다.",
    "EXTENDED_DESCRIPTION": ["이제 변환 된 공격 카드와 스킬 카드가 소멸하지 않습니다."]
  },
  "Moonworks:MixPhenomenon": {
    "NAME": "믹스화 현상",
    "DESCRIPTION": "무작위 기프트카드 !M! 장의  moonworks:사용횟수 를 복구하여 뽑을 카드 더미에 섞어넣습니다. NL 카드를 !Moonworks:SecondMagic! 장 뽑습니다. NL 소멸.",
    "UPGRADE_DESCRIPTION": "기프트카드 !M! 장의  moonworks:사용횟수 를 복구하여 뽑을 카드 더미에 섞어넣습니다. NL 카드를 !Moonworks:SecondMagic! 장 뽑습니다. NL 소멸."
  },
  "Moonworks:NicePresent": {
    "NAME": "근사한 선물",
    "DESCRIPTION": "카드를 !M! 장 뽑습니다. NL 소멸.",
    "EXTENDED_DESCRIPTION": ["뽑은 카드가 이번 턴 동안 보존 됩니다."]
  },
  "Moonworks:OutOfAmmo": {
    "NAME": "탄약 소진",
    "DESCRIPTION": "손에 카드가 없거나, moonworks:기프트 혹은 사용불가 상태이상 카드만 있을 경우 카드를 한 장 뽑습니다."
  },
  "Moonworks:PlushieMaster": {
    "NAME": "인형 마스터",
    "DESCRIPTION": " moonworks:인형표식 을 무작위 적에게 !M! 부여합니다.",
    "EXTENDED_DESCRIPTION": ["표식이 2 증가합니다."]
  },
  "Moonworks:Poppoformation": {
    "NAME": "폿포메이션",
    "DESCRIPTION": "다음 !M! 번 동안 적의 의도에 따라 약화, 손상, 혹은 취약을 부여합니다."
  },
  "Moonworks:PortablePudding": {
    "NAME": "휴대용 푸딩",
    "DESCRIPTION": "턴 종료시 마다 체력을 !M! 회복합니다."
  },
  "Moonworks:ProtagonistsPrivilege": {
    "NAME": "주인공의 특권",
    "DESCRIPTION": "피해를 !D! 줍니다. NL 카드를 !M! 장 뽑습니다. NL 뽑은 두 카드의 종류가 같으면, 이 *효과 를 다음 턴에도 발동시킵니다.",
    "EXTENDED_DESCRIPTION": ["막히지 않은 피해를 주면 체력을 !Moonworks:SecondMagic! 회복합니다."]
  },
  "Moonworks:QuickRestoration": {
    "NAME": "순간 재생",
    "DESCRIPTION": "방어도 를 !B! 만큼 !M! 번 얻습니다.",
    "EXTENDED_DESCRIPTION": ["얻는 방어도가 1 줄어들지만, 얻는 횟수가 1 늘어납니다."]
  },
  "Moonworks:RagingMadness": {
    "NAME": "뚜껑 폭발",
    "DESCRIPTION": "막히지 않은 피해를 받을 때 마다 힘 을 !M! 얻습니다.",
    "UPGRADE_DESCRIPTION": "선천성. NL 막히지 않은 피해를 받을 때 마다 힘 을 !M! 얻습니다.",
    "EXTENDED_DESCRIPTION": ["얻는 힘 이 2배가 됩니다."]
  },
  "Moonworks:RainbowColoredCircle": {
    "NAME": "Rainbow-Colored Circle",
    "DESCRIPTION": "Convert !M! Block into moonworks:Steady.",
    "EXTENDED_DESCRIPTION": ["+4 Block Conversion and *Optimize.","Optimized","This card always converts at least #b5 #yBlock, but it will convert more, determined by your current #yBlock and the intent of your enemies."]
  },
  "Moonworks:RedAndBlue": {
    "NAME": "아카와 아오",
    "DESCRIPTION": "moonworks:사용횟수 !Moonworks:SecondMagic!. NL 턴 시작시 활력 을 !M! 얻고 moonworks:굳건함 을 !M! 얻습니다. NL 사용 시 이 카드를 버립니다.",
    "EXTENDED_DESCRIPTION": ["아카와 아오가 쉬고있습니다."]
  },
  "Moonworks:ReflectiveShell": {
    "NAME": "반사 외갑",
    "DESCRIPTION": "다음 번에 체력을 잃는 것을 막아줍니다. 막은 피해 만큼 활력 을 얻습니다."
  },
  "Moonworks:ReproductionOfRecords": {
    "NAME": "기록의 재현(스미카 스위트 메모리)",
    "DESCRIPTION": "버린 카드 더미 맨 위의 카드 !M! 장을 복사해 손에 가져옵니다. NL 소멸.",
    "UPGRADE_DESCRIPTION": "보존. NL 버린 카드 더미 맨 위의 카드 !M! 장을 복사해 손에 가져옵니다. NL 소멸.",
    "EXTENDED_DESCRIPTION": ["[E] 를 얻습니다."]
  },
  "Moonworks:Rival": {
    "NAME": "라이벌",
    "DESCRIPTION": "체력이 가장 높은 적이 당신의 moonworks:라이벌 이 됩니다."
  },
  "Moonworks:RocketCannon": {
    "NAME": "로켓포",
    "DESCRIPTION": "피해를 !D! 줍니다. NL *빅 *로켓포 !M! 장을 뽑을 카드 더미에 섞어넣습니다.",
    "EXTENDED_DESCRIPTION": ["*빅 *로켓포 를 한 장 추가로 섞어넣습니다."]
  },
  "Moonworks:SakisCookie": {
    "NAME": "사키의 쿠키",
    "DESCRIPTION": "다음 세 효과중 하나가 무작위로 발동합니다: NL 체력을 !M! 회복합니다. NL 활력 을 !Moonworks:ThirdMagic! 얻습니다. NL moonworks:굳건함 을 !Moonworks:ThirdMagic! 얻습니다.",
    "EXTENDED_DESCRIPTION": ["효과가 *최적화 됩니다","최적화된 쿠키","잃은 체력이 있으면 항상 체력을 회복합니다. NL 적이 공격할 의도가 있고 손에 방어도 를 얻는 카드가 있다면 활력 대신 굳건함 을 얻습니다."]
  },
  "Moonworks:ScrambledEve": {
    "NAME": "스크램블드 이브",
    "DESCRIPTION": "카드를 원하는 만큼 선택해 버리고, 버린 카드 + !M! 장 만큼 카드를 뽑습니다.",
    "UPGRADE_DESCRIPTION": "버린 카드 더미를 뽑을 카드 더미에 넣고 섞습니다. NL 카드를 원하는 만큼 선택해 버리고, 버린 카드 + !M! 장 만큼 카드를 뽑습니다.",
    "EXTENDED_DESCRIPTION": ["카드를 1 장 더 뽑습니다", "카드를 1 장 더 뽑습니다"]
  },
  "Moonworks:SealedMemories": {
    "NAME": "기억 봉인",
    "DESCRIPTION": "손에 있는 카드를 1 장 까지 선택해 *전환 합니다. NL 이번 턴 동안 손패를 보존합니다.",
    "UPGRADE_DESCRIPTION": "보존. NL 손에 있는 카드를 1 장 까지 선택해 *전환 합니다. NL 이번 턴 동안 손패를 보존합니다.",
    "EXTENDED_DESCRIPTION": ["기억 전환","비용이 1 이상인 #y공격 또는 #y스킬 카드만 전환할 수 있습니다."]
  },
  "Moonworks:SelfDestruct": {
    "NAME": "자폭",
    "DESCRIPTION": "moonworks:고정 *피해 를 !Moonworks:InvertedNumber! 받습니다. NL 모든 적에게 피해를 !D! 줍니다. NL 자가 피해에는 방어도 가 !Moonworks:SecondMagic! 배 더 효과적입니다. NL *속박 중에도 사용할 수 있습니다.",
    "EXTENDED_DESCRIPTION": ["자가 피해가 X 감소합니다."]
  },
  "Moonworks:SeriousBattle": {
    "NAME": "진검 승부",
    "DESCRIPTION": "대상에게 무작위 !M! 장의 moonworks:기억 효과를 발동시킵니다.",
    "UPGRADE_DESCRIPTION": "대상에게 선택한 최대 !M! 장의 moonworks:기억 효과를 발동시킵니다."
  },
  "Moonworks:ShieldCounter": {
    "NAME": "실드 반전",
    "DESCRIPTION": "방어도 를 !B! 얻습니다. NL moonworks:실드반전 을 1 얻습니다. NL 소멸.",
    "EXTENDED_DESCRIPTION": ["moonworks:실드반전 에 *넘겨주기 가 적용됩니다."]
  },
  "Moonworks:SinkOrSwim": {
    "NAME": "가라앉거나 헤엄치거나",
    "DESCRIPTION": "턴 시작시 [E] [E] 를 얻습니다. NL 다음 !Moonworks:SecondMagic! 턴 동안 취약, 약화, 손상 을 1 씩 받습니다."
  },
  "Moonworks:StarBlastingFuse": {
    "NAME": "별의 도화선",
    "DESCRIPTION": "moonworks:보이지않는폭탄 을 설치합니다. NL 이 카드를 뽑을 카드 더미에 섞어넣습니다. NL 이 카드를 뽑을 경우, moonworks:보이지않는폭탄 이 설치된 모든 적은 체력을 !M! 잃습니다.",
    "EXTENDED_DESCRIPTION": ["쾅!","후후후, 터져볼래?","재밌게 해주지 않겠니?"]
  },
  "Moonworks:StarBlastingLight": {
    "NAME": "별을 불태우는 빛",
    "DESCRIPTION": "모든 적에게 !M! 에서 !Moonworks:SecondMagic! 사이의 moonworks:불태우는빛 을 부여합니다. NL Purge.",
    "EXTENDED_DESCRIPTION": ["부여하는 moonworks:불태우는빛 이 X 증가합니다.",
      "후후... 아하하!","자, 재가 될 때 까지...","예쁘게 타오르렴."]
  },
  "Moonworks:StiffCrystal": {
    "NAME": "견고한 수정",
    "DESCRIPTION": "인공물 을 !M! 얻습니다. NL 방어도 를 !B! 얻습니다. NL 소멸.",
    "EXTENDED_DESCRIPTION": ["방어도 가 4 증가합니다."]
  },
  "Moonworks:Strike": {
    "NAME": "타격",
    "DESCRIPTION": "피해를 !D! 줍니다.",
    "EXTENDED_DESCRIPTION": ["피해가 1 증가합니다.", "피해가 2 증가합니다."]
  },
  "Moonworks:SubspaceTunnel": {
    "NAME": "아공간 터널",
    "DESCRIPTION": "아무 카드 더미에서 카드를 한 장 선택합니다. NL 선택한 카드와 이 카드의 위치를 서로 바꿉니다. NL 선택한 카드는 이번 턴 동안 비용이 0이 됩니다."
  },
  "Moonworks:SweetBattle": {
    "NAME": "스위트 배틀!",
    "DESCRIPTION": "moonworks:사용횟수 !Moonworks:SecondMagic!. NL 이 카드를 뽑거나 보존 시, 뽑을 카드 더미에 *사키의 *쿠키 1 장을 섞어넣습니다. NL *사키의 *쿠키 의 효과가 2 증가하고, moonworks:자동소모 됩니다. NL 사용 시 이 카드를 버립니다.",
    "EXTENDED_DESCRIPTION": ["당이 떨어졌습니다."]
  },
  "Moonworks:TacticalRetreat": {
    "NAME": "36계 줄행랑",
    "DESCRIPTION": "방어도를 !B! 얻습니다. NL 다음 턴에, [E] 를 얻고 방어도 를 !M! 얻습니다.",
    "EXTENDED_DESCRIPTION": ["얻는 방어도 가 2 증가합니다."]
  },
  "Moonworks:TreasureThief": {
    "NAME": "보물 도둑",
    "DESCRIPTION": "턴 마다 한 번, 대상에게 피해를 줄 때 마다 카드를 !M! 장 뽑습니다. NL 소멸.",
    "EXTENDED_DESCRIPTION": ["턴 마다 한 번, 대상에게 피해를 줄 때 마다 50% 확률로 카드를 한 장 더 뽑습니다."]
  },
  "Moonworks:Ubiquitous": {
    "NAME": "신출귀몰",
    "DESCRIPTION": "잠깐! 이 카드를 어떻게 얻은거죠? NL 이 카드를 써서 좋을 건 없을겁니다, 확실히요..."
  },
  "Moonworks:UnluckyCharm": {
    "NAME": "불행의 부적",
    "DESCRIPTION": "moonworks:사용횟수 !Moonworks:SecondMagic!. NL 모든 대상이 임시 민첩 을 !Moonworks:InvertedNumber! 잃습니다. NL 소멸 시, 민첩 을 !M! 얻습니다. NL 이 카드는 사용하여 버릴 수 없습니다.",
    "EXTENDED_DESCRIPTION": ["부적이 사라지자 운이 조금 좋아진 기분이 듭니다."]
  },
  "Moonworks:UnpaidWork": {
    "NAME": "무급 노동",
    "DESCRIPTION": "다음에 사용하는 카드가 [#FFF6E2]Purge 되지 않고 비용이 1 이상일 경우, 비용을 [#FFF6E2]Refund 받습니다. NL 소멸."
  },
  "Moonworks:WarudaMachine": {
    "NAME": "와루다 머신",
    "DESCRIPTION": "moonworks:발진! 을 준비합니다. 와루다 머신이 moonworks:발진! 하기 전에 대상이 죽을 경우, 효과가 무작위 대상에게 옮겨가고 수치가 2배로 증가합니다 NL 소멸.",
    "EXTENDED_DESCRIPTION": ["*스킬 카드를 뽑을 때 까지 카드를 뽑습니다."]
  },
  "Moonworks:Wanted": {
    "NAME": "현상수배",
    "DESCRIPTION": "대상에게 moonworks:현상수배 를 !M! 부여합니다. NL 소멸.",
    "UPGRADE_DESCRIPTION": "보존. NL 대상에게 moonworks:현상수배 를 !M! 부여합니다. NL 소멸."
  },
  "Moonworks:WeAreWaruda": {
    "NAME": "우리는 와루다",
    "DESCRIPTION": "모든 대상의 해로운 효과를 제거합니다. NL 제거된 효과를 한 대상에게 모두 부여합니다. NL 소멸."
  },
  "Moonworks:WhiteChristsmasher": {
    "NAME": "화이트 크리스매셔",
    "DESCRIPTION": "피해를 !D! 만큼 2번 줍니다. NL 손에  *아카와 *아오 가 있을 경우, 이 피해를 모든 적에게 줍니다.",
    "EXTENDED_DESCRIPTION": ["진 화이트 크리스매셔","모든 적에게 피해를 !D! 만큼 2번 줍니다."]
  },
  "Moonworks:WhimsicalWindmill": {
    "NAME": "변덕쟁이 풍차",
    "DESCRIPTION": "턴 시작 시, 이전 턴에 자신을 공격한 적의 수 만큼 추가로 에너지 를 얻습니다.",
    "UPGRADE_DESCRIPTION": "선천성. NL 턴 시작 시, 이전 턴에 자신을 공격한 적의 수 만큼 추가로 에너지 를 얻습니다."
  },
  "Moonworks:WindyEnchantment": {
    "NAME": "질풍의 인챈트",
    "DESCRIPTION": "moonworks:사용횟수 !Moonworks:SecondMagic!. NL 뽑을 때, 카드를 2 장 뽑습니다. NL 보존 시, 카드를 !M! 장 뽑습니다. NL 사용 시, 이 카드를 버립니다",
    "EXTENDED_DESCRIPTION": ["순풍이 사그라들었습니다."]
  },
  "Moonworks:x16BigRocket": {
    "NAME": "빅 로켓",
    "DESCRIPTION": "피해를 !D! 줍니다. 이번 전투 동안 이 카드의 피해가  !M! 증가합니다. NL x16 빅 로켓으로 강화 될 수 있습니다."
  },
  "Moonworks:AttackTextContainer": {
    "NAME": "Generic Attack Text",
    "DESCRIPTION": "Extended Description used to hold text that will occasionally appear when playing an attack.",
    "EXTENDED_DESCRIPTION": ["타버리렴.","잿더미로.","빵.","아하하하하!"]
  },
  "Moonworks:SkillTextContainer": {
    "NAME": "Generic Skill Text",
    "DESCRIPTION": "Extended Description used to hold text that will occasionally appear when playing a skill.",
    "EXTENDED_DESCRIPTION": ["우후후.","자아.","이렇게?"]
  },
  "Moonworks:PowerTextContainer": {
    "NAME": "Generic Power Text",
    "DESCRIPTION": "Extended Description used to hold text that will occasionally appear when playing a power.",
    "EXTENDED_DESCRIPTION": ["좋아, 써줄게!","어떻게 되려나.","써볼까."]
  },
  "Moonworks:BattleStartTextContainer": {
    "NAME": "Battle Start Text",
    "DESCRIPTION": "Extended Description used to hold text that will occasionally appear at the beginning of combat.",
    "EXTENDED_DESCRIPTION": ["재밌게 해주지 않겠니?","좋아, 상대해줄게.","후후후... 사냥감이 왔네..","제발로 불타러 온거야?"]
  },
  "Moonworks:LowHPBattleStartTextContainer": {
    "NAME": "Low HP Battle Start Text",
    "DESCRIPTION": "Extended Description used to hold text that will occasionally appear at the beginning of combat if you are badly injured.",
    "EXTENDED_DESCRIPTION": ["싫은데, 좀!","거슬려.","이런것에...","짜증나."]
  },
  "Moonworks:BattleEndTextContainer": {
    "NAME": "Battle End Text",
    "DESCRIPTION": "Extended Description used to hold text that will occasionally appear at the end of combat.",
    "EXTENDED_DESCRIPTION": ["예쁘게 타올랐어!","전-부 예쁜 것들.","아하하하하하하!","이제 끝.","우후후, 새까매"]
  },
  "Moonworks:BossFightTextContainer": {
    "NAME": "Boss Fight Text",
    "DESCRIPTION": "Extended Description used to hold text that will occasionally appear at the beginning of a boss fight.",
    "EXTENDED_DESCRIPTION": ["나왔다! 굉장한 게!","아하하! 재밌어졌어.","기세 좋게 탈 것 같네."]
  },
  "Moonworks:HealingTextContainer": {
    "NAME": "Healing Text",
    "DESCRIPTION": "Extended Description used to hold text that will occasionally appear when healing.",
    "EXTENDED_DESCRIPTION": ["아직 게속할 수 있어...","후후... 기분 좋아.","이제 더 싸울 수 있어","괜찮아..","이제 아프지 않아! 아하하!"]
  },
  "Moonworks:FieldDamageTextContainer": {
    "NAME": "Field Damage Text",
    "DESCRIPTION": "Extended Description used to hold text that will occasionally appear when taking thorns damage.",
    "EXTENDED_DESCRIPTION": ["꺅!","아으.","큭.","잘도..."]
  },
  "Moonworks:LightDamageTextContainer": {
    "NAME": "Light Damage Text",
    "DESCRIPTION": "Extended Description used to hold text that will occasionally appear when taking light damage.",
    "EXTENDED_DESCRIPTION": ["좀.","아으.","이런...","크으."]
  },
  "Moonworks:HeavyDamageTextContainer": {
    "NAME": "Heavy Damage Text",
    "DESCRIPTION": "Extended Description used to hold text that will occasionally appear when taking heavy damage.",
    "EXTENDED_DESCRIPTION": ["이게 아니야.","아파... 아파아아아!","아파!","이런 걸로.","으으으으으."]
  },
  "Moonworks:BlockedDamageTextContainer": {
    "NAME": "Blocked Damage Text",
    "DESCRIPTION": "Extended Description used to hold text that will occasionally appear when blocking damage.",
    "EXTENDED_DESCRIPTION": ["아핫!","안 닿아.","무슨 일 있었어?"]
  },
  "Moonworks:HomemarkTextContainer": {
    "NAME": "Homemark Text",
    "DESCRIPTION": "Extended Description used to hold text that will occasionally appear when spending gold with the Homemark.",
    "EXTENDED_DESCRIPTION": ["좀, 사라져 버렸잖아.","후후후, 뿔뿔이.","이렇게 많이는 필요하지 않은데.","이 동전, 거추장스럽네.","하아, 이런 것보다 전쟁을 하고싶어."]
  },
  "Moonworks:KOTextContainer": {
    "NAME": "KO Text",
    "DESCRIPTION": "Extended Description used to hold text that will occasionally appear when defeated in battle.",
    "EXTENDED_DESCRIPTION": ["내가... 이럴수가.","지는 나한테는 아무런 의미도 없어...","이게 무슨... 나는 무엇 때문에?","이, 이런 거에 지다니......","나는 이겨야만 하는데... 이겨야만!"]
  }
}
